anews/__init__.py
anews/common/FFmpeg.py
anews/common/VideoEffect.py
anews/common/__init__.py
anews/common/config.py
anews/common/drawhelper.py
anews/common/utils.py
anews/dao/__init__.py
anews/dao/texthelper.py
anews/dao/msn/__init__.py
anews/dao/sound/__init__.py
anews-1.30.dist-info/METADATA
anews-1.30.dist-info/WHEEL
anews-1.30.dist-info/top_level.txt
anews-1.30.dist-info/RECORD
