Metadata-Version: 2.1
Name: anews
Version: 1.30
Summary: A Des of anews
Home-page: https://github.com/vtandroid/anews
Author: Thanh Hoa
Author-email: getmoneykhmt3@gmail.com
License: UNKNOWN
Platform: UNKNOWN
Classifier: Programming Language :: Python :: 3
Classifier: License :: OSI Approved :: MIT License
Classifier: Operating System :: OS Independent
Requires-Dist: pillow
Requires-Dist: requests
Requires-Dist: gbak
Requires-Dist: w3lib
Requires-Dist: python-slugify
